Workbook
Name Aporte: APP!$D$13
Name Patrimonio: APP!$D$16
Name Periodo: APP!$D$14
Name Rendimento: APP!$D$17
Name Rendimento_Carteira: APP!$D$9
Name Taxa_Mensal: APP!$D$15

Sheet APP
B7: CONFIGURAÇÕES
B8: Salário | D8: 2000
B9: Rendimento de Carteira | D9: 0.006
B10: Sugestão de Investimento | D10: =D8*30% -> 600
B12: INVESTIMENTO MENSAL
B13: Quanto investir por mês? | D13: 200
B14: Por quantos anos? | D14: 5
B15: Taxa de rendimento mensal? | D15: 0.01079
B16: Patrimônio acumulado? | D16: =FV(Taxa_Mensal,Periodo*12,Aporte*-1) -> 16755.383
B17: Dividendos mensais? | D17: =Patrimonio*Rendimento_Carteira -> 100.5323
B19: CENÁRIOS | D19: DIVIDENDOS
A20: 2 | B20: Quanto em 2 anos? | C20: =FV($D$15,$A20*12,$D$13)*-1 -> 5445.5255 | D20: =C20*Rendimento_Carteira -> 32.673153
A21: 5 | B21: Quanto em 5 anos? | C21: =FV($D$15,$A21*12,$D$13)*-1 -> 16755.383 | D21: =C21*Rendimento_Carteira -> 100.5323
A22: 10 | B22: Quanto em 10 anos? | C22: =FV($D$15,$A22*12,$D$13)*-1 -> 48656.843 | D22: =C22*Rendimento_Carteira -> 291.94106
A23: 20 | B23: Quanto em 20 anos? | C23: =FV($D$15,$A23*12,$D$13)*-1 -> 225039.68 | D23: =C23*Rendimento_Carteira -> 1350.2381
A24: 30 | B24: Quanto em 30 anos? | C24: =FV($D$15,$A24*12,$D$13)*-1 -> 864433.93 | D24: =C24*Rendimento_Carteira -> 5186.6036
B27: PERFIL | C27: AGRESSIVO
B28: VALOR A SER INVESTIDO POR MÊS | C28: =Aporte -> 200
B30: TIPO DE FII | C30: PERCENTUAL SUGERIDO | D30: VALORES
B31: PAPEL | C31: =VLOOKUP($C$27&"-"&B31,'TABELA DE APOIO'!$B:$E,4,FALSE) -> 0.5 | D31: =$C$28*C31 -> 100
B32: TIJOLO | C32: =VLOOKUP($C$27&"-"&B32,'TABELA DE APOIO'!$B:$E,4,FALSE) -> 0.1 | D32: =$C$28*C32 -> 20
B33: HÍBRIDOS | C33: =VLOOKUP($C$27&"-"&B33,'TABELA DE APOIO'!$B:$E,4,FALSE) -> 0.05 | D33: =$C$28*C33 -> 10
B34: FOF | C34: =VLOOKUP($C$27&"-"&B34,'TABELA DE APOIO'!$B:$E,4,FALSE) -> 0.05 | D34: =$C$28*C34 -> 10
B35: DESENVOLVIMENTO | C35: =VLOOKUP($C$27&"-"&B35,'TABELA DE APOIO'!$B:$E,4,FALSE) -> 0.2 | D35: =$C$28*C35 -> 40
B36: HOTELARIA | C36: =VLOOKUP($C$27&"-"&B36,'TABELA DE APOIO'!$B:$E,4,FALSE) -> 0.1 | D36: =$C$28*C36 -> 20
D37: =SUM(D31:D36) -> 200

Sheet TABELA DE APOIO
B2: CHAVE | C2: PERFIL | D2: TIPO DE FII | E2: %
B3: CONSERVADOR-PAPEL | C3: CONSERVADOR | D3: PAPEL | E3: 0.3
B4: CONSERVADOR-TIJOLO | C4: CONSERVADOR | D4: TIJOLO | E4: 0.5
B5: CONSERVADOR-HÍBRIDOS | C5: CONSERVADOR | D5: HÍBRIDOS | E5: 0.1
B6: CONSERVADOR-FOF | C6: CONSERVADOR | D6: FOF | E6: 0.1
B7: CONSERVADOR-DESENVOLVIMENTO | C7: CONSERVADOR | D7: DESENVOLVIMENTO | E7: 0
B8: CONSERVADOR-HOTELARIA | C8: CONSERVADOR | D8: HOTELARIA | E8: 0
B9: MODERADO-PAPEL | C9: MODERADO | D9: PAPEL | E9: 0.32
B10: MODERADO-TIJOLO | C10: MODERADO | D10: TIJOLO | E10: 0.35
B11: MODERADO-HÍBRIDOS | C11: MODERADO | D11: HÍBRIDOS | E11: 0.08
B12: MODERADO-FOF | C12: MODERADO | D12: FOF | E12: 0.05
B13: MODERADO-DESENVOLVIMENTO | C13: MODERADO | D13: DESENVOLVIMENTO | E13: 0.1
B14: MODERADO-HOTELARIA | C14: MODERADO | D14: HOTELARIA | E14: 0.1
... B20: AGRESSIVO-HOTELARIA | C20: AGRESSIVO | D20: HOTELARIA | E20: 0.1
